{
  "hash": "049761db",
  "configHash": "c2cc6a0a",
  "lockfileHash": "95a58566",
  "browserHash": "c5a539f4",
  "optimized": {
    "vue": {
      "src": "../../../node_modules/vue/dist/vue.runtime.esm-bundler.js",
      "file": "vue.js",
      "fileHash": "0e58209e",
      "needsInterop": false
    },
    "vitepress > @vue/devtools-api": {
      "src": "../../../node_modules/@vue/devtools-api/dist/index.js",
      "file": "vitepress___@vue_devtools-api.js",
      "fileHash": "8da90e01",
      "needsInterop": false
    },
    "vitepress > @vueuse/core": {
      "src": "../../../node_modules/@vueuse/core/index.mjs",
      "file": "vitepress___@vueuse_core.js",
      "fileHash": "a9318822",
      "needsInterop": false
    },
    "@theme/index": {
      "src": "../../../node_modules/vitepress/dist/client/theme-default/index.js",
      "file": "@theme_index.js",
      "fileHash": "936f5324",
      "needsInterop": false
    }
  },
  "chunks": {
    "chunk-WZSWIX5T": {
      "file": "chunk-WZSWIX5T.js"
    },
    "chunk-Z6B2QTD3": {
      "file": "chunk-Z6B2QTD3.js"
    }
  }
}